knn_distinguish/__init__.py
knn_distinguish/pDistinguisher.py
knn_distinguish-0.0.1.dist-info/METADATA
knn_distinguish-0.0.1.dist-info/WHEEL
knn_distinguish-0.0.1.dist-info/top_level.txt
knn_distinguish-0.0.1.dist-info/RECORD
